{"id":"1115019","title":"玉楼春","dynasty":"宋","author":"杜安世","text":"玉烛光明正旦好。斗柄东回春太早。岭寒犹锁去年梅，江暖新催今岁草。蜀国熙熙冬令杪。更喜寿阳新梦觉。玉杯齐举乐音谐，遥想金阶天仗晓。风解池冰蝉翅薄。庭树枝枯笼翠萼。背寒迎暖起犹慵，闲卷珠帘凭画阁。晴景融融烟漠漠。天际行人乖信约。病容先怯见春来，长到恁时添瘦削。晴景融融春色浅。落尽梅花千万片。小池冰解水纹生，消息未闻梁上燕。楼倚轻寒风力软。目断孤云天自远。又还依旧去年时，寂寞病容人怪见。三月牡丹呈艳态。壮观人间春世界。鲛绡玉槛作扃栊，淹雅洞中王母队。不奈风吹兼日㬠。国貌天香无物赛。直须共赏莫轻孤，回首万金何处买。纶命忽从天上至。便绾兵权辞漕计。汉廷起草旧郎官，蜀部坐筹新将帅。红旆碧幢春色里。娇马嘶风花片坠。送行今日短亭中，恼乱故人须尽醉。春景抛人无处问。多谢石榴花又喷。茜罗揉出碎英繁，红蜡缕成香萼润。血色新裙羞莫近。密叶柔条相间衬。雨馀寂寞假山傍，乡国尚遥西海信。三月初三春渐老。遍地残花风暗扫。命俦啸侣拥笙歌，临水泛觞游宴好。浮利浮名何足道。丽景芳时须笑傲。今年不似去年欢，云海路长天杳杳。"}