{"id":"1235215","title":"饮酒五首","dynasty":"元","author":"马祖常","text":"进士当盛明，自谓非时才。狂斐学文字，无圣为我裁。二者俱寡合，终令智士咍。斯旦已阳春，对我聊持杯。祖母在堂上，小孙方稚孩。俯仰见五世，居生岂悠哉。简编有重讹，折衷无权衡。黎庶有重困，救药无持平。昔者贤圣出，屯蹇踬其身。踬身不踬道，龙蛇果能伸。弃置姑饮酒，陶然会天真。万物各遂性，杂沓向我陈。考妣早弃我，得禄不逮亲。幸兹有祖母，九十康强身。我情终不乐，日思我亲仁。襁抱免水火，少长俾知伦。出入邹鲁俗，用变宿习因。植松在淮山，稼田为齐民。兴念辄涕泣，有酒亦逡巡。昔我七世上，养马洮河西。六世徙天山，日日闻鼓鼙。金室狩河表，我祖先群黎。诗书百年泽，濡翼岂梁鹈。尝观汉建国，再世有日磾。后来兴唐臣，胤裔多羌氐。春秋圣人法，诸侯乱冠笄。夷礼即夷之，毫发各有稽。吾生赖陶化，孔阶力攀跻。敷文佐时运，烂烂应璧奎。嗟哉寡谐合，苍发秃不齐。觞至即饮嚼，犹恐逢诃诋。众人以儒进，我不限吏资。入官养交誉，惟恐不合时。含笑作雅咏，遭骂亦诡随。出入践华要，諈诿成其私。积阶渐崇贵，剽猎章句辞。鼓颊说古今，證据称云为。斯世岂可诬，小夫甘自欺。兴言发喟叹，饮者终不知。"}