{"id":"239776","title":"咏石得天字","dynasty":"宋代","author":"宋无名","text":"肢胍昆仑析，胚浑混沌先。灵分玄岛峙，秀聚景云群。覆压风雷窟，枝撑宇宙穿。崚嶒欹条雾，历吵声萝烟。几业栖危壁，磷磷过瘦涓。雨攻缉眼断，涩声弹窜圆。笔架珊瑚竖，屏圉玛阵偏。骨攒狞鬼竦，脊凸老蛟跧。剑卓空苍色，矛森紫翠颠。丑宜铱鸟篆，刚可利龙泉。怪浦潮纹涞，顽和地轴连，筼簹梢映带，薜功叶萦缠。磊磈蛇身缩，崩峥风势偏。藓侵题宇处，藤络倚筇边。碎砾铺文贝，尖峰斫黛莲。宝深膏乳滴，甃润土花沿。砂若峨冠者，昂如峻干焉。磴危欺木屐，砚滑怯苔氈。移恐岚光动，扪嗔野蔓牵。术濡声类声，汪瀑韵成统。碣性辞斤盘，嵌形欠画傅。鼓歌伤莫续，鼎句叹难聊。砥厣诚由著，磨砻学及迁。畜奇希所璞，煉饵诧飞仙。寸势垂千仇，嵬胎结岁年。岩晖知产玉，峡束见奔川。织女支机稳，山人作枕便。陨星沈战域，敲火出渔船。异或称斗化，疑应讶虎眠。龟进遗歇下，麟仆古萱前。屹立中流壮，平施大礎竖。怀沙嗟放逐，凝魄惜婵娟。德必穹碑纪，词当巨砚研。险思经滟滪，功拟勒燕然。嵩贷归诸掌，蓬瀛寄一叛。不须填碧海，直欲补青天。"}