{"id":"256129","title":"无题十二行","dynasty":"现代","author":"羊令野","text":"第一帖每一次走过那峭立的岩壁你的脚音就摹临出汉魏碑意铿锵亦如悲凉的志文重复一则柔美的故事水准一样清澈的你的名字回转于那条曲巷里仿佛三月的羽觞盛着满满的酒香缓缓流向我的小小的书屋忙碌的云趁着雨后张罗吩咐那些高高低低的野树抱山而来把我们秘藏在春意最深最浓处祇允许月光入夜酝酿第二帖昨夜我的冷冽把你揉成雪今朝你的体温把我溶为水究竟想用雪还是水酿一尊清得澈骨的春酒等所有的花都开了等所有的鸟都啼过剩下一座无声无色的空山能否赶上一片闲云共住就让酒还给水水还给雪雪还给云云和我们还给天地第三帖尽管河床还躺在春雨的梦里你的弦上汨汨而来的流水已经漫过了我心中隐隐飞桥偶然窥见掠起的雪裳云裾缥缈间山水的腰身远远横陈那最熟悉的背影若果一星如月引领陌生的天路走去该当闻及云的疲倦的脚音落向岑寂的银河两岸第四帖背后一片峭壁飞来面前一泓清流静止谁用金属的回声喊你把你的影子暗中引渡引渡中的影子是一袭浮沉的云裳它的名字腐蚀在未定的方向也许霜冷之后必然雪白而影子渐渐隐入地平线而回声淹没了远方潮汐"}