{"id":"257209","title":"灰 鼠","dynasty":"现代","author":"于坚","text":"不请自来的小坏蛋在我房间里建立了据点神出鬼没从来不打照面晚上在电视里看到你的大名和唐老鸭并列方知你是明星我再也不得安宁了灰鼠已来到我的房间像是一个瘤子已长在我身体内部多次去医院透视什么也没有查出我的馒头被锯掉一半我的大米有可疑的黑斑到底作案者是谁我开始小心翼翼竖耳谛听听听衣柜听听地板我当然搜到那细小而坚硬的声音可我无法断定你小子是在咬我心爱的衬衣还是在啃外公留给我的古玩你总是轻溜溜地走动似乎出于对我的关心从前外祖母也喜欢如此在深夜悄悄下床关好风中的窗子你在蛋糕上跳舞在药片上撒尿把我的好书咬得百孔千疮但毕竟你不知道什么会响什么不会于是撞翻瓷器又跳过某个高度居然造成一回地震吓得我从梦中逃出踮起脚尖又不能勃然大怒还必须干得比你更轻从床头摸到书架担心着被你听见似乎你正在写作不能打扰我比你笨拙终于撞倒了椅子我惶惶然东张西望显得心中有愧其实你小子或许已酣然睡去喝了牛奶换了一个套间你在暗处转动着两粒黑豆似的眼珠看见我又大又笨一丝不挂毫无风度你发现我在夜里的样子你保持沉默这一点和父亲不同这种品德使我深觉难堪我终于不能忍受乱敲乱捅找决定彻底搜查把你逮捕处死但一看到周围这些庞大无比的家俱那些隐藏在无数什物中的掩体我就心烦意乱茫然失措只好放弃行动外面都以为我独处一室必定神清思静潜心学问其实我担惊受怕避免出门一下班就匆匆回家一进门就打开柜子打开箱子检查那个不露声色的家伙又干了些什么勾当"}