{"id":"262434","title":"情人节手提青菜和鱼去看你","dynasty":"现代","author":"朵朵","text":"今天是二月十四日而你躺在离我十分钟步行七站地铁八分钟步行的一张床上我只能左手提一把青菜右手挽一条鱼穿过熙熙攘攘的玫瑰花穿过手拉手的情侣穿过地铁检票口穿过三十二分钟去那个小屋探望你你在病中今天是情人节多希望我左手一束鲜花右手一条三五可是我却左手一束青菜右手一条鱼因为你说你喜欢我的蒜蓉青菜红烧鱼因为今天你在病里我只能放弃想象了半年的烛光晚餐路过每个时髦女子专卖店我都来不及盘算换下脚上这双被你拉坏了拉锁的紫色短靴在起风的黄昏五点半我只想知道你的厨房里有没有正宗的八角胡椒道地的酱油老蔡据说大多数人生病时会想起妈妈的温暖我只有放下纵横了多日的刁钻涂点唇彩装作温柔面带笑容因为哥几个都说你曾经有一个漂亮的女朋友一个富有的女朋友和一个爱你的女朋友你看我不够漂亮不够富有甚至不够爱你除了温柔我什么也没有除了温柔我什么都没有书上说抓住一个男人的胃就能抓住他的心你看我一路胡思乱想最后还是提着一把青菜一条鱼来敲门一个小时以后它们就会变成我送你的维生素和纤维素而那条离开水多时的鱼也许会比我的舌头更加美味你看亲爱的我小心翼翼带着两个糖衣炮弹趁虚而入来看你你要不还是快点扶病而起穿好你小心翼翼准备的防弹衣"}