{"id":"457873","title":"一日，安徒生之美人鱼遇漆园吏之曳尾龟，乃相与谈。其言鱼嚏鳖咳，盖不能悉。鱼陋龟之无文也，诺为之寄书，而请其友鲛人代购之。鲛人者，中文版之美人鱼也。龟得书，欲以诗相谢，而自顾龟爪短拙，不能捉笔，转请诸碰壁斋。碰壁斋才尽，然感二鱼之义，且与龟同出庄子之门，于是强头咬牙，硬拼蛮做，终焉成章。龟受而读之，摇头摆尾，团团自转，不胜其雀跃云。诗曰","dynasty":"当代","author":"卢青山","text":"网上江湖水，中有美人鱼。盈盈掉长尾，悠悠自卷舒。行行忽惊诧，对面者谁欤？背甲厚成尺，匍地行崎岖；跛泳借四足，欹侧其身躯。相逢亦不易，通姓问何如。一曰安徒生，一曰庄周徒。一居晶宫里，贝阙耸云衢；临窗偶顾盼，鳞介尽疯愚。一居水陆隙，曳尾在泥涂；兽既视我异，鳞亦与我疏；孤行不自惜，日与影相娱。鱼曰“子无伤，与子行相俱；我复有佳友，子或尝闻诸；其名为鲛人，其人态甚姝；惜哉隔千里，不得共驰驱”。行行各别去，异日来邮舆；开缄鲛人泪，化为掌上珠；剖珠何所得，得此奇人书。嗟二美人鱼，情好何殊殊；龟究何物尔，亦得分其馀。寄诗远相谢，诗者碰壁居。"}