{"id":"686290","title":"金陵八景 钟阜朝云","dynasty":"明","author":"史谨","text":"山形高立翠芙蓉，岩际晴云万朵封。起映朝阳成五色，化为霖雨锁千峰。飞扬或乱松间鹤，舒卷长随洞底龙。欲访招提无处觅，数声惟听隔林钟。石露苔痕雪渐晞，晨光相映晃朝衣。千章璚树为幢列，一路彤云映日飞。阵影度壕鸦散墨，女墙开冻玉生辉。忽乘瘦蹇寻梅过，多少人家尚掩扉。黑云拖雨过长汀，恍若骊珠散紫清。声到枕边惊蝶梦，风回蓬底带龙腥。渔灯隐隐孤村暗，芦叶萧萧两岸鸣。已觉夜深还淅沥，满怀羁思不堪听。万里无云月正中，倚阑人在广寒宫。数行雁落天边影，一曲笙传鹤背风。香拂几筵飘桂子，露含光彩滴梧桐。夜深转觉清无寐，卧看冰轮碾碧空。夹路青山拥翠螺，每闻樵唱隔烟萝。暗惊鹤梦穿云杪，细答松声出涧阿。几度半酣扶杖听，有时一曲傍林过。晚来弛担长松下，复和岩前扣角歌。一汀红蓼缀残霞，两两渔舟泊浅沙。横笛共吹无调曲，隔林惊散并栖鸦。声回野岸沈蛟室，响拂江风起浪花。多少天涯未归客，夜深听罢却思家。深巷迢迢接九垓，巷南巷北尽楼台。帘栊自放斜阳入，王谢难随燕子来。花斗春光云锦簇，山含暮景画图开。几番醉拂吟鞭过，树影重重压翠苔。一江晴绿漾微波，顷刻平堤雨夜过。暖汎桃花随画鹢，倒涵树影拂银河。群鸥卧藻堆残雪，双鹭窥鱼立细莎。何日系舟杨柳岸，酒酣濯足听渔歌。"}