{"id":"816374","title":"游箱根","dynasty":"清","author":"黄遵宪","text":"危涂远盘纡，径仄鸟迹绝。一步不敢前，双足若被刖。人呼兜笼来，纵横宽尺八。脚手垂郎当，腰背盘曲折。舆人出裸国，皮绉龟兆裂。螭蛟绣满身，横胸施绛袜。两肩乍抬举，双杖互扶挈。前枝后更撑，仰攀俯若跌。有如蚁旋磨，又似蛇出穴。跦跦上竹点，蠢蠢爬沙鳖。噫风竹筒吹，汗雨蒸甑泄。劳倦时一歌，乡音鸟嘲哳。烟树绕千回，风花眩一瞥。峭壁俯绝壑，旁睨每挢舌。四山呼无人，一堕便永诀。畏途宁中止，弛担娄更迭。直穷绝顶高，始觉天地阔。群峰插云中，结屋峰头住。濛濛万云海，凭空无寸土。开窗起看云，迷茫若无睹。一云忽飞来，一云不肯去。一云幻作龙，盘旋绕层柱。关窗急遮拦，攒隙细如缕。须臾塞破屋，真气满庭户。解装张行囊，呼童共捞取。大风卷地来，团作黑烟聚。隐隐闻雷声，乍似婴儿怒。遥知百万家，已洒三尺雨。我方跂脚眠，梦骑赤龙舞。直倾天河水，远向并豫注。侧身起西望，梦堕云深处。举国无名川，一湖何滉瀁！环抱三百里，下窥五十丈。神武开辟来，亘古无消长。氿泉日穴出，洑流失归向。一碧湛空明，万象绝依傍。昂头只日月，两轮互摩荡。我来驾一舟，杳茫迷所往。谓是沧溟游，乘风破巨浪。何图众山顶，乃泛海荡荡。关东昔豪杰，割地争霸王。汤池据此险，漆城莫敢上。迩来司农官，又作填海想。凿脉乾此湖，可得千沃壤。纷纷校得失，尧桀我俱忘。且作烟波徒，容与打双桨。群山若堂防，依严各构屋。家家争调水，曲笕引修竹。泠泠滴檐角，汩汩出严腹。晓鸦犹未兴，已有游人浴。东屋鸣琴弦，西屋斗棋局。南屋垂钓竿，北屋罗简牍。蛟毫展凉簟，鹤?被轻服。点白茶始尝，堆红果初熟。蕃舶从海来，蒲萄泛新渌。洪崖揖浮丘，萧史媚弄玉。鸡犬亦飞升，熊鱼各得欲。人生贵行乐，矧此神仙福。缠腰更骑鹤，辟俗还食肉。平生烟霞心，奈此桑下宿。行携《桃源图》，归我筼筜谷。"}