{"id":"863880","title":"酬种放徵君一百韵","dynasty":"宋","author":"王禹称","text":"太岁在辛卯，九月万木落。是时太阴亏，占云臣道剥。王生出紫微，谴逐走商洛。扶亲又抱子，迤逦过京索。弊车载书史，病马悬囊橐。西都不敢住，空负香山约。阌乡正南路，秦岭峭如削。肩舆碍巨石，十步三四却。妻孥亦徒步，碛砾不容脚。山店盖木皮，烟火浑熏灼。夜深闻贙虎，全家屡惊戄。山泉何萦回，切冽无桥彴。卸鞍引羸蹄，解袜事芒屩。晨澜发可鉴，朝涉胫如斮。商山六百里，天设皆岩崿。上洛在其中，狴牢曾未若。逐臣自可死，何必在远恶。刺史不我顾，古寺聊淹泊。卜居杂民氓，致养无精糳。知道由自宽，有亲强为乐。侧闻种先生，终南卧云壑。长沮既躬耕，元礼仍开学。王绩妇未娶，介洁翘孤鹤。之推母偕隐，教诲脩天爵。诗情亦嗜酒，道气不服药。田衣剪荷芰，野饭烹茝蒻。雾豹泽文彩，冥鸿避矰缴。肯从羔雁聘，唯恐簪裾缚。如何宋右史，斥鴳议雕鹗。玄纁与丹诏，恩礼诚非薄。仍敕京兆府，敦谕辞恭恪。先生恋板舆，纯孝心坚确。散发走烟峦，拜章谢恩渥。巨材犹在涧，大玉不出璞。使者遂空回，软轮何寂寞。贤母召徵君，庭责词嗃嗃。胡为事章句，漏名入街郭。府县污我山，胥徒噪吾幄。以兹近声利，安得成高邈。誓将徙穷谷，庶可逃喧浊。先生拜引过，为寿开樽杓。陶陶又熙熙，何啻闻竽籥。人传到迁客，面目敦惭怍。器小识不远，当年事头角。遭时得一第，游宦何龌龊。逐膻甚蚍蜉，斗耀同??。宰邑乏弦歌，谏垣无謇谔。便蕃朱紫绶，僭忝丝纶阁。方号骙骙龙，已困狺狺㹱。待罪始知非，咄哉昧先觉。一聆高世行，罪发庸可擢。忍耻赋三章，尘埃寄寥廓。明年会恩宥，量移井蛙跃。靡暇谒南山，征途望西岳。黄河波汹涌，白径苔班驳。中条围解县，五老烟龊龊。此焉为郡副，乌敢事陨穫。笼禽幸未死，尚且谋饮啄。米呼村婢舂，樵雇山僮斫。喂马捽寒芜，看书爇秋箨。信口亦吟哦，放心无适莫。君恩已绝望，人事终难度。相府一张纸，唤起久屈蠖。诚知有梁栋，未忍弃榱桷。五城天上开，三殿云间卓。重取故衣冠，笼裹山猱玃。病翼得风云，坏墙劳赭垩。谏官与史氏，旧职聊羁络。举袖拂石螭，凝眸睨金雀。冥心想前事，一梦何挥矐。长恐先生闻，倚松成大噱。关中朋友来，遗我神仙作。繁华远客骑，铮鏦美人错。古澹啜铏羹，文雅铿木铎。千言距百韵，旨趣何绰绰。孰念气如虹，翻然轻抵鹊。俊甚麻姑抓，快比屠门嚼。浑金岂在镕，尺璧宁施琢。愈风齐捧檄，忘味同闻乐。致之向怀袖，日夕芬兰若。褒我尘俗韵，铅刀化干镆。同声必有应，过实还疑谑。盛夸山中事，云屋张霞幕。兰芽含露采，石髓和烟酌。巢由泉涤耳，园绮芝盈握。有时上绝顶，星斗近可摸。下视尘世人，营营似螶?。男儿既束发，出处岐路各。苟非秉陶钧，即去持矛槊。致主比唐虞，安边如卫霍。不尔为逸人，深居返吾朴。胡然自碌碌，名节日销铄。行年过半世，功业欠圭勺。无术铸五兵，使民兴钱镈。无材统六师，逐寇开沙漠。空言说王道，肆眼看人瘼。多惭指佞草，虚效倾心藿。一览大雅文，起予亦何博。况兹山野性，谟画昧方略。搔首谢朝簪，行将返耕凿。"}